LICENSE
README.md
setup.cfg
setup.py
dev/__init__.py
dev/__main__.py
dev/constants.py
dev/exceptions.py
dev/files.py
dev/loader.py
dev/main.py
dev/output.py
dev/process.py
dev/setup.py
dev/timer.py
dev/version.py
dev/linters/__init__.py
dev/linters/base.py
dev/linters/csharp.py
dev/linters/css.py
dev/linters/javascript.py
dev/linters/php.py
dev/linters/python.py
dev/linters/typescript.py
dev/linters/utils.py
dev/tasks/__init__.py
dev/tasks/build.py
dev/tasks/chain.py
dev/tasks/clean.py
dev/tasks/count.py
dev/tasks/custom.py
dev/tasks/doc.py
dev/tasks/index.py
dev/tasks/install.py
dev/tasks/lint.py
dev/tasks/publish.py
dev/tasks/run.py
dev/tasks/spell.py
dev/tasks/task.py
dev/tasks/test.py
dev/tasks/time.py
dev/tasks/uninstall.py
dev/tasks/unused.py
dev_star.egg-info/PKG-INFO
dev_star.egg-info/SOURCES.txt
dev_star.egg-info/dependency_links.txt
dev_star.egg-info/entry_points.txt
dev_star.egg-info/not-zip-safe
dev_star.egg-info/requires.txt
dev_star.egg-info/top_level.txt