Metadata-Version: 2.1
Name: dev-star
Version: 1.3.0
Summary: Dev tools CLI for performing common development tasks.
Home-page: https://dev.terrytm.com
Author: Terry Zheng
Author-email: contact@terrytm.com
Maintainer: Terry Zheng
Maintainer-email: contact@terrytm.com
License: Apache 2.0
Project-URL: Bug Reports, https://dev.terrytm.com/issues
Project-URL: Documentation, https://dev.terrytm.com
Project-URL: Source Code, https://github.com/TerrayTM/dev
Keywords: developer tools
Classifier: Development Status :: 5 - Production/Stable
Classifier: Intended Audience :: Developers
Classifier: License :: OSI Approved :: Apache Software License
Classifier: Programming Language :: Python
Classifier: Programming Language :: Python :: 3.8
Requires-Python: >=3.8
License-File: LICENSE
Requires-Dist: isort
Requires-Dist: black
Requires-Dist: tqdm
Requires-Dist: pyyaml
Requires-Dist: twine
Requires-Dist: pylint
